boto_rsync
