Metadata-Version: 1.0
Name: boto-rsync
Version: 0.5.3
Summary: An rsync-like wrapper for boto's S3 and Google Storage interfaces.
Home-page: http://github.com/seedifferently/boto_rsync
Author: Seth Davis
Author-email: seth@curiasolutions.com
License: MIT
Keywords: boto amazon aws s3 gs google storage cloud sync rsync
Platform: Posix; MacOS X; Windows
Classifier: Development Status :: 3 - Alpha
Classifier: Environment :: Console
Classifier: Intended Audience :: Developers
Classifier: Intended Audience :: System Administrators
Classifier: License :: OSI Approved :: MIT License
Classifier: Programming Language :: Python
Classifier: Topic :: Utilities
